[
    {
        "title": "Dr. Aarya Venkat successfully defends his PhD! Congratulations!",
        "date": "November 1, 2023",
        "image": "images/news.png",
        "link": "./"
    },
    {
        "title": "Dr. Safal Shrestha successfully defends his PhD! Congratulations!",
        "date": "October 30, 2023",
        "image": "images/news.png",
        "link": "./"
    },
    {
        "title": "Natarajan Kannan receives the Lamar Dodd creative research award! Congratulations!",
        "date": "April 4, 2023",
        "image": "images/news.png",
        "link": "https://iob.uga.edu/dr-natarajan-kannan-receives-lamar-dodd-creative-research-award-congratulations-dr-kannan/"
    },
    {
        "title": "Nathan and Maya both receive intramural travel awards to attend IDG conference! Congratulations!",
        "date": "June 4, 2023",
        "link": "./"
    },
    {
        "title": "Natarajan Kannan receives Lamar Dodd creative research award!",
        "date": "Apr 4, 2023",
        "link": "https://iob.uga.edu/dr-natarajan-kannan-receives-lamar-dodd-creative-research-award-congratulations-dr-kannan/"
    },
    {
        "title": "Aarya Venkat recieves ASBMB Travel Award to present an oral talk at the ASBMB conference!",
        "date": "Mar 27, 2023",
        "link": "./"
    },
    {
        "title": "Aarya Venkat wins Poster Award at the Society for Glycobiology Conference! Congratulations!",
        "date": "Nov 17, 2022",
        "link": "./"
    },
    {
        "title": "Grace Watterson presents her work on DCLK kinases at the Harden Conference in the UK!",
        "date": "Nov 2, 2022",
        "link": "./"
    },
    {
        "title": "Maya Salcedo receives ARCS foundation scholarship! Congratulations!!",
        "date": "Aug 8, 2022",
        "link": "https://www.bmb.uga.edu/news/stories/2022/reagan-haney-and-mariah-salcedo-win-2022-arcs-scholarship"
    },
    {
        "title": "Zhongliang Zhou wins the outstanding graduate student award at the University of Georgia! Congratulations!",
        "date": "Jul 31, 2022",
        "link": "./"
    },
    {
        "title": "George Bendzunas wins first place for poster at Winship Cancer Retreat, Congratulations!",
        "date": "July 25, 2022",
        "link": "./"
    },
    {
        "title": "Dr. Wayland Yeung graduates with a PhD from the Kannan lab, congratulations!",
        "date": "Apr 18, 2022",
        "link": "./"
    },
    {
        "title": "Claire Bunn named Gates-Cambridge Scholar and NIH Oxford Scholar, congratulations!",
        "date": "Aug 10, 2021",
        "link": "https://news.uga.edu/claire-bunn-named-gates-cambridge-scholar/"
    },
    {
        "title": "Aarya Venkat receives ARCS Foundation Award, congratulations!",
        "date": "Aug 10, 2021",
        "link": "https://www.bmb.uga.edu/news/stories/2021/aarya-venkat-receives-2021-22-arcs-foundation-award"
    },
    {
        "title": "Kannan Lab reaches 4500 citations!",
        "date": "May 14, 2021",
        "link": "./"
    },
    {
        "title": "Niral Thaker is going to Med School! Congratulations!",
        "date": "Apr 30, 2021",
        "link": "./"
    },
    {
        "title": "Dr. Rahil Taujale graduates with a PhD from the Kannan Lab, congratulations!",
        "date": "Apr 19, 2021",
        "link": "./"
    },
    {
        "title": "Claire Bunn named 2021 Goldwater Scholar, congratulations!",
        "date": "Apr 16, 2021",
        "link": "https://www.genetics.uga.edu/news/stories/2021/claire-bunn-named-2021-goldwater-scholar"
    },
    {
        "title": "Dr. Leon Huang graduates with a PhD from the Kannan Lab, congratulations!",
        "date": "Apr 12, 2021",
        "link": "./"
    },
    {
        "title": "Aarya Venkat wins Three Minute Thesis and $500 award. Congratulations!",
        "date": "Apr 9, 2021",
        "link": "https://news.uga.edu/10th-annual-three-minute-thesis-competition/"
    },
    {
        "title": "Kannan Lab receives prestigious MIRA (R35) grant.",
        "date": "July 7, 2020",
        "link": "https://news.uga.edu/kannan-receives-2m-nih-mira-award/"
    },
    {
        "title": "New Publication in Science Signaling.",
        "date": "July 7, 2020",
        "link": "./"
    },
    {
        "title": "Claire Bunn receives NIH summer research internship. CONGRATULATIONS!!",
        "date": "May 1, 2020",
        "link": "./"
    },
    {
        "title": "Aarya Venkat named one of 2019-2020 Future Faculty Fellows. Congratulations!!",
        "date": "Aug 20, 2019",
        "link": "./"
    },
    {
        "title": "Annie Kwon highlighted in an article on her pseudokinase research by UGA Research!",
        "date": "Aug 15, 2019",
        "link": "https://news.uga.edu/graduate-students-work-on-so-called-dead-enzymes-proves-their-significance/"
    },
    {
        "title": "Annie Kwon successfully defended her dissertation. CONGRATULATIONS!!",
        "date": "Apr 17, 2019",
        "link": "./"
    },
    {
        "title": "Zheng Ruan receives the Graduate Student Excellence-in-Research Award 2019. CONGRATULATIONS!!",
        "date": "Apr 12, 2019",
        "link": "./"
    },
    {
        "title": "Aarya Venkat receives the Outstanding Teaching Assistant Award.",
        "date": "Feb 27, 2018",
        "link": "./"
    },
    {
        "title": "Publication in Science Signaling featured in the online cover.",
        "date": "Sept 25, 2018",
        "link": "./"
    },
    {
        "title": "Zheng Ruan successfully defended his dissertation!! CONGRATULATIONS!!",
        "date": "Dec 1, 2017",
        "link": "./"
    },
    {
        "title": "Annie Kwon is awarded the Franklin-Liverpool Fellowship. CONGRATULATIONS!!",
        "date": "Dec 1, 2017",
        "link": "./"
    },
    {
        "title": "Zheng Ruan is awarded the 2017 innovative and interdisciplinary research grant. CONGRATULATIONS!!",
        "date": "Apr 21, 2017",
        "link": "./"
    },
    {
        "title": "Rahil Taujale is awarded the Glycoscience Training Program Fellowship. CONGRATULATIONS!!",
        "date": "Dec 19, 2016",
        "link": "./"
    },
    {
        "title": "KinView is published on ProKinO",
        "date": "Oct 22, 2016",
        "link": "./"
    },
    {
        "title": "Our Lab Receives New NIH Grant",
        "date": "Aug 1, 2015",
        "link": "./"
    },
    {
        "title": "Tuan Nguyen receives the Goldwater Scholarship.",
        "date": "June 27, 2014",
        "link": "./"
    },
    {
        "title": "Eric Talevich secures a post-doctoral position at UCSF.",
        "date": "Aug 1, 2013",
        "link": "./"
    },
    {
        "title": "Dr. Kannan wins the NSF Career Award.",
        "date": "June 5, 2012",
        "link": "./"
    }
]